cardisort/__init__.py
cardisort-0.1.1.dist-info/METADATA
cardisort-0.1.1.dist-info/RECORD
cardisort-0.1.1.dist-info/WHEEL
cardisort-0.1.1.dist-info/top_level.txt
