Metadata-Version: 2.1
Name: cardisort
Version: 0.1.1
Summary: Cardiac MR DICOM sorting
Home-page: https://github.com/cianmscannell/cardisort
Author: Cian M. Scannell, Ruth P. Lim
Author-email: cian.scannell@kcl.ac.uk
License: CC BY-NC-SA 4.0
Platform: UNKNOWN
Classifier: Development Status :: 1 - Planning
Classifier: Programming Language :: Python :: 3
Classifier: License :: Free for non-commercial use
Classifier: Operating System :: OS Independent
